async_retriever/__init__.py
async_retriever/_utils.py
async_retriever/async_retriever.py
async_retriever/exceptions.py
async_retriever/print_versions.py
async_retriever/py.typed
async_retriever/streaming.py
async_retriever-0.19.3.dist-info/METADATA
async_retriever-0.19.3.dist-info/WHEEL
async_retriever-0.19.3.dist-info/licenses/AUTHORS.rst
async_retriever-0.19.3.dist-info/licenses/LICENSE
async_retriever-0.19.3.dist-info/RECORD
