Metadata-Version: 2.4
Name: async-retriever
Version: 0.19.3
Summary: High-level API for asynchronous requests with persistent caching.
Project-URL: Changelog, https://docs.hyriver.io/changelogs/async-retriever.html
Project-URL: CI, https://github.com/hyriver/async-retriever/actions
Project-URL: Homepage, https://docs.hyriver.io/readme/async-retriever.html
Project-URL: Issues, https://github.com/hyriver/async-retriever/issues
Author-email: Taher Chegini <cheginit@gmail.com>
License: MIT
License-File: AUTHORS.rst
License-File: LICENSE
Classifier: Development Status :: 4 - Beta
Classifier: Framework :: AsyncIO
Classifier: Intended Audience :: Developers
Classifier: License :: OSI Approved :: MIT License
Classifier: Operating System :: OS Independent
Classifier: Programming Language :: Python
Classifier: Programming Language :: Python :: 3 :: Only
Classifier: Programming Language :: Python :: 3.9
Classifier: Programming Language :: Python :: 3.10
Classifier: Programming Language :: Python :: 3.11
Classifier: Programming Language :: Python :: 3.12
Classifier: Programming Language :: Python :: 3.13
Classifier: Topic :: Internet :: WWW/HTTP
Classifier: Typing :: Typed
Requires-Python: >=3.9
Requires-Dist: aiodns
Requires-Dist: aiofiles
Requires-Dist: aiohttp-client-cache>=0.12.3
Requires-Dist: aiohttp>=3.8.3
Requires-Dist: aiosqlite
Requires-Dist: brotli
Requires-Dist: cytoolz
Requires-Dist: multidict
Requires-Dist: orjson<4,>=3.10
Requires-Dist: yarl
Provides-Extra: test
Requires-Dist: pytest-cov; extra == 'test'
Requires-Dist: pytest-sugar; extra == 'test'
Requires-Dist: shapely; extra == 'test'
